python_mumps-0.0.2.dist-info/LICENSE
python_mumps-0.0.2.dist-info/WHEEL
python_mumps-0.0.2.dist-info/RECORD
python_mumps-0.0.2.dist-info/METADATA
mumps/fortran_helpers.py
mumps/_version.py
mumps/__init__.py
mumps/mumps.py
mumps/_mumps.cpython-311-x86_64-linux-gnu.so
mumps/tests/test_mumps.py
mumps/tests/__init__.py
mumps/tests/_test_utils.py
python_mumps.libs/libpord_seq-5-34f67f45.2.1.so
python_mumps.libs/libdmumps_seq-5-b7436db2.2.1.so
python_mumps.libs/libmumps_common_seq-5-ab361a45.2.1.so
python_mumps.libs/libquadmath-7463de5d.so.0.0.0
python_mumps.libs/libopenblasp-r0-c6542500.3.26.so
python_mumps.libs/libgfortran-0a5141d4.so.5.0.0
python_mumps.libs/libcmumps_seq-5-b7f14bbd.2.1.so
python_mumps.libs/libscotcherr-6-bea597e7.so
python_mumps.libs/libscotch-6-47a92858.so
python_mumps.libs/libzmumps_seq-5-7fb1a8d0.2.1.so
python_mumps.libs/libsmumps_seq-5-ddbc5a91.2.1.so
python_mumps.libs/libmetis-416bc986.so
python_mumps.libs/libesmumps-6-2b88a5fe.so
