Metadata-Version: 2.1
Name: python-mumps
Version: 0.0.2
Summary: Bindings and Python interface for the MUMPS sparse solver
Home-page: https://gitlab.kwant-project.org/kwant/python-mumps
Author-Email: Python-MUMPS authors <authors@kwant-project.org>
License: BSD 2-Clause License
Classifier: Development Status :: 3 - Alpha
Classifier: Intended Audience :: Science/Research
Classifier: Intended Audience :: Developers
Classifier: Programming Language :: Python :: 3 :: Only
Classifier: Topic :: Scientific/Engineering
Classifier: Operating System :: POSIX
Classifier: Operating System :: Unix
Classifier: Operating System :: MacOS :: MacOS X
Classifier: Operating System :: Microsoft :: Windows
Project-URL: Homepage, https://gitlab.kwant-project.org/kwant/python-mumps
Requires-Python: >=3.9
Requires-Dist: numpy>=1.23
Requires-Dist: scipy>=1.8
